setup.py
Flask_SAResource.egg-info/PKG-INFO
Flask_SAResource.egg-info/SOURCES.txt
Flask_SAResource.egg-info/dependency_links.txt
Flask_SAResource.egg-info/not-zip-safe
Flask_SAResource.egg-info/requires.txt
Flask_SAResource.egg-info/top_level.txt
flask_saresource/__init__.py
flask_saresource/resource.py