Metadata-Version: 1.1
Name: Flask-SAResource
Version: 0.1.1
Summary: Flask extension for building routes from SQLAlchemy models
Home-page: https://www.github.com/mmautner/flask-saresource/
Author: Max Mautner
Author-email: max@mustknow.io
License: BSD
Platform: any
Classifier: Environment :: Web Environment
Classifier: Intended Audience :: Developers
Classifier: License :: OSI Approved :: BSD License
Classifier: Operating System :: OS Independent
Classifier: Programming Language :: Python
Classifier: Topic :: Internet :: WWW/HTTP :: Dynamic Content
Classifier: Topic :: Software Development :: Libraries :: Python Modules
